athena/__init__.py
athena/cli.py
athena/broadcasting/__init__.py
athena/broadcasting/mailing.py
athena/broadcasting/slack.py
athena/broadcasting/templates/datamail.html
athena/queries/__init__.py
athena/queries/query.py
athena/scheduling/__init__.py
athena/scheduling/celeryconfig.py
athena/scheduling/scheduler.py
athena/utils/__init__.py
athena/utils/cluster.py
athena/utils/config.py
athena/utils/file.py
athena/utils/ssh.py
athena/utils/tunnel.py
athena-0.8.0.dist-info/DESCRIPTION.rst
athena-0.8.0.dist-info/entry_points.txt
athena-0.8.0.dist-info/METADATA
athena-0.8.0.dist-info/metadata.json
athena-0.8.0.dist-info/RECORD
athena-0.8.0.dist-info/top_level.txt
athena-0.8.0.dist-info/WHEEL
